Workbook

Sheet README
A1: Zenora Dental — Sales Operations Workbook
A2: WhiteFox AI · built 6 Aug 2026 · all currency in INR (₹)
B5: HOW TO USE THIS FILE
B6: Pipeline | C6: Your CRM. One row per prospect. Update 'Stage' as deals move. Everything on Dashboard reads from here.
B7: Prospect List | C7: Where you build the raw list before qualifying. Move a row into Pipeline once it clears the checks.
B8: Pricing Calculator | C8: Change the yellow cells to model a specific deal. Shows year-1 value and your true margin.
B9: Revenue Model | C9: 12-month projection. Change the yellow assumptions at the top and everything below recalculates.
B10: Dashboard | C10: Read-only summary. Conversion rates, pipeline value, and where deals are dying.
B12: COLOUR CODE
B13: Yellow cells | C13: Inputs — you edit these.
B14: Blue text | C14: Hardcoded numbers you can change.
B15: Black text | C15: Formulas — do not overwrite; they will recalculate on their own.
B17: HEALTHY BENCHMARKS
B18: Cold email → reply | C18: 8–15%
B19: Reply → demo booked | C19: ~40%
B20: Demo → closed won | C20: 25–35%. Below 20% means you are qualifying too loosely, not demoing badly.
B21: Time to live | C21: 7 days or less — this is a core promise, so track it.
B22: Monthly churn | C22: Under 5%
B24: BEFORE YOU CHARGE ANYONE
B25: Read the gap report | C25: 05_Production_Readiness_Gap_Report.md lists three blockers that must close before a paying clinic goes live.
B26: Do not demo Analytics | C26: The revenue figures in that tab are hardcoded sample data. Demo Command Center instead.

Sheet Pipeline
A1: Pipeline
A2: One row per prospect. Update Stage as the deal moves. Dashboard reads from this sheet.
A3: ↓ Row 5 is a filled-in example. Overwrite it with your first real prospect.
A4: Clinic Name | B4: Owner (Dr.) | C4: City | D4: Phone | E4: Email | F4: Source | G4: Google Rating | H4: Reviews | I4: Has Website? | J4: Running Ads? | K4: Tier Pitched | L4: Setup (₹) | M4: Monthly (₹) | N4: Yr-1 Value (₹) | O4: Stage | P4: Next Action | Q4: Next Action Date | R4: Notes
A5: Smile Craft Dental | B5: Dr. Anjali Rao | C5: Pune | D5: +91 98XXXXXX21 | E5: hello@smilecraft.in | F5: Meta Ad Library | G5: 4.7 | H5: 132 | I5: No | J5: Yes | K5: Professional | L5: 44999 | M5: 2499 | N5: =IF(L5="","",L5+M5*12) -> 74987 | O5: Demo Booked | P5: Run 15-min demo, lead with Command Center | Q5: 2026-08-12 | R5: Running ads to a page with no booking form — lead with wasted ad spend
N6: =IF(L6="","",L6+M6*12)
N7: =IF(L7="","",L7+M7*12)
N8: =IF(L8="","",L8+M8*12)
N9: =IF(L9="","",L9+M9*12)
N10: =IF(L10="","",L10+M10*12)
N11: =IF(L11="","",L11+M11*12)
N12: =IF(L12="","",L12+M12*12)
N13: =IF(L13="","",L13+M13*12)
N14: =IF(L14="","",L14+M14*12)
N15: =IF(L15="","",L15+M15*12)
N16: =IF(L16="","",L16+M16*12)
N17: =IF(L17="","",L17+M17*12)
... N204: =IF(L204="","",L204+M204*12)

Sheet Prospect List
A1: Prospect List — raw sourcing
A2: Build the list here. A row that scores 3+ qualifying marks is ready to move into Pipeline.
A3: Qualify Score: +1 each for rating ≥4 · reviews ≥20 · no booking form · running ads · single owner. 3+ = worth contacting.
A4: Clinic Name | B4: City / Area | C4: Source | D4: Google Rating | E4: Reviews | F4: Website Status | G4: Booking Form? | H4: Running Ads? | I4: Single Owner? | J4: Qualify Score | K4: Ready? | L4: Found On
A5: Smile Craft Dental | B5: Pune – Kothrud | C5: Meta Ad Library | D5: 4.7 | E5: 132 | F5: Facebook page only | G5: No | H5: Yes | I5: Yes | J5: =IF(A5="","",(IF(D5>=4,1,0))+(IF(E5>=20,1,0))+(IF(G5="No",1,0))+(IF(H5="Yes",1,0))+(IF(I5="Yes",1,0))) -> 5 | K5: =IF(A5="","",IF(J5>=3,"MOVE TO PIPELINE","Keep looking")) -> MOVE TO PIPELINE | L5: 2026-08-06
J6: =IF(A6="","",(IF(D6>=4,1,0))+(IF(E6>=20,1,0))+(IF(G6="No",1,0))+(IF(H6="Yes",1,0))+(IF(I6="Yes",1,0))) | K6: =IF(A6="","",IF(J6>=3,"MOVE TO PIPELINE","Keep looking"))
J7: =IF(A7="","",(IF(D7>=4,1,0))+(IF(E7>=20,1,0))+(IF(G7="No",1,0))+(IF(H7="Yes",1,0))+(IF(I7="Yes",1,0))) | K7: =IF(A7="","",IF(J7>=3,"MOVE TO PIPELINE","Keep looking"))
J8: =IF(A8="","",(IF(D8>=4,1,0))+(IF(E8>=20,1,0))+(IF(G8="No",1,0))+(IF(H8="Yes",1,0))+(IF(I8="Yes",1,0))) | K8: =IF(A8="","",IF(J8>=3,"MOVE TO PIPELINE","Keep looking"))
J9: =IF(A9="","",(IF(D9>=4,1,0))+(IF(E9>=20,1,0))+(IF(G9="No",1,0))+(IF(H9="Yes",1,0))+(IF(I9="Yes",1,0))) | K9: =IF(A9="","",IF(J9>=3,"MOVE TO PIPELINE","Keep looking"))
J10: =IF(A10="","",(IF(D10>=4,1,0))+(IF(E10>=20,1,0))+(IF(G10="No",1,0))+(IF(H10="Yes",1,0))+(IF(I10="Yes",1,0))) | K10: =IF(A10="","",IF(J10>=3,"MOVE TO PIPELINE","Keep looking"))
J11: =IF(A11="","",(IF(D11>=4,1,0))+(IF(E11>=20,1,0))+(IF(G11="No",1,0))+(IF(H11="Yes",1,0))+(IF(I11="Yes",1,0))) | K11: =IF(A11="","",IF(J11>=3,"MOVE TO PIPELINE","Keep looking"))
J12: =IF(A12="","",(IF(D12>=4,1,0))+(IF(E12>=20,1,0))+(IF(G12="No",1,0))+(IF(H12="Yes",1,0))+(IF(I12="Yes",1,0))) | K12: =IF(A12="","",IF(J12>=3,"MOVE TO PIPELINE","Keep looking"))
J13: =IF(A13="","",(IF(D13>=4,1,0))+(IF(E13>=20,1,0))+(IF(G13="No",1,0))+(IF(H13="Yes",1,0))+(IF(I13="Yes",1,0))) | K13: =IF(A13="","",IF(J13>=3,"MOVE TO PIPELINE","Keep looking"))
J14: =IF(A14="","",(IF(D14>=4,1,0))+(IF(E14>=20,1,0))+(IF(G14="No",1,0))+(IF(H14="Yes",1,0))+(IF(I14="Yes",1,0))) | K14: =IF(A14="","",IF(J14>=3,"MOVE TO PIPELINE","Keep looking"))
J15: =IF(A15="","",(IF(D15>=4,1,0))+(IF(E15>=20,1,0))+(IF(G15="No",1,0))+(IF(H15="Yes",1,0))+(IF(I15="Yes",1,0))) | K15: =IF(A15="","",IF(J15>=3,"MOVE TO PIPELINE","Keep looking"))
J16: =IF(A16="","",(IF(D16>=4,1,0))+(IF(E16>=20,1,0))+(IF(G16="No",1,0))+(IF(H16="Yes",1,0))+(IF(I16="Yes",1,0))) | K16: =IF(A16="","",IF(J16>=3,"MOVE TO PIPELINE","Keep looking"))
J17: =IF(A17="","",(IF(D17>=4,1,0))+(IF(E17>=20,1,0))+(IF(G17="No",1,0))+(IF(H17="Yes",1,0))+(IF(I17="Yes",1,0))) | K17: =IF(A17="","",IF(J17>=3,"MOVE TO PIPELINE","Keep looking"))
... J304: =IF(A304="","",(IF(D304>=4,1,0))+(IF(E304>=20,1,0))+(IF(G304="No",1,0))+(IF(H304="Yes",1,0))+(IF(I304="Yes",1,0))) | K304: =IF(A304="","",IF(J304>=3,"MOVE TO PIPELINE","Keep looking"))

Sheet Pricing Calculator
A1: Pricing Calculator
A2: Edit the yellow cells to model one specific deal.
B4: DEAL INPUTS
B5: Setup fee (₹) | C5: 44999 | D5: Professional tier list price
B6: Monthly fee (₹) | C6: 2499 | D6: Professional tier list price
B7: Setup discount (%) | C7: 0 | D7: Founding client = 0.40. Never discount the monthly.
B8: Annual prepay? (1=yes) | C8: 0 | D8: 1 = client pays 12 months up front, gets 2 free
B9: Contract length (months) | C9: 12
B11: REVENUE
B12: Net setup fee | C12: =C5*(1-C7) -> 44999
B13: Months billed | C13: =IF(C8=1,10,C9) -> 12 | D13: Annual prepay bills 10 months for 12 months of service
B14: Subscription revenue | C14: =C6*C13 -> 29988
B15: TOTAL CONTRACT VALUE | C15: =C12+C14 -> 74987
B17: YOUR COSTS
B18: Hosting per clinic / month (₹) | C18: 200 | D18: Vercel + Atlas + Resend, amortised across clinics on shared tiers
B19: Domain per year (₹) | C19: 1200 | D19: Only if you include it — Professional and Clinic Plus do
B20: Your build hours | C20: 14 | D20: Realistic for a per-clinic deploy today, per the gap report
B21: Your hourly rate (₹) | C21: 1500 | D21: What your time is actually worth
B22: Support hours / month | C22: 0.5 | D22: Realistic steady state. Budget 3-4 hours in month 1.
B24: Build cost | C24: =C20*C21 -> 21000
B25: Hosting over term | C25: =C18*C9 -> 2400
B26: Support cost over term | C26: =C22*C21*C9 -> 9000
B27: TOTAL COST | C27: =C24+C25+C26+C19 -> 33600
B29: RESULT
B30: Gross profit | C30: =C15-C27 -> 41387
B31: Blended gross margin | C31: =IFERROR(C30/C15,0) -> 0.55192233 | D31: Build labour included. This is a services margin, not a SaaS margin — 50-65% is healthy.
B32: Effective hourly rate | C32: =IFERROR(C30/(C20+C22*C9),0) -> 2069.35 | D32: What you actually earned per hour on this deal
B33: Payback on build cost | C33: =IFERROR((C24-C12)/C6,0) -> -9.6034414 | D33: Months of subscription to recover build cost after the setup fee. Negative = paid back on day one.
B35: SUBSCRIPTION ECONOMICS (the number that matters long-term)
B36: Monthly revenue | C36: =C6 -> 2499
B37: Monthly cost to serve | C37: =C18+(C22*C21) -> 950 | D37: Hosting + support only. Build cost is one-off and already recovered by the setup fee.
B38: Monthly gross profit | C38: =C36-C37 -> 1549
B39: Subscription margin | C39: =IFERROR(C38/C36,0) -> 0.61984794 | D39: This is the recurring margin. It should sit well above 60% - if not, raise the price or cut support time.
B41: Assumption: hosting cost is per-clinic and assumes several clinics share one Vercel Pro / MongoDB Atlas M10 instance.
B42: One clinic alone on paid tiers costs roughly ₹3,000/month and is close to break-even at the Professional price. See Sales Playbook §5.

Sheet Revenue Model
A1: 12-Month Revenue Model
A2: Edit the yellow assumptions. Everything below recalculates.
B4: ASSUMPTIONS
B5: New clients per month | C5: 2
B6: Avg setup fee (₹) | C6: 44999
B7: Avg monthly fee (₹) | C7: 2499
B8: Monthly churn rate | C8: 0.03
B9: Hosting cost per client (₹) | C9: 200
B12: Month | C12: M1 | D12: M2 | E12: M3 | F12: M4 | G12: M5 | H12: M6 | I12: M7 | J12: M8 | K12: M9 | L12: M10 | M12: M11 | N12: M12
B13: New clients | C13: =$C$5 -> 2 | D13: =$C$5 -> 2 | E13: =$C$5 -> 2 | F13: =$C$5 -> 2 | G13: =$C$5 -> 2 | H13: =$C$5 -> 2 | I13: =$C$5 -> 2 | J13: =$C$5 -> 2 | ... N13: =$C$5 -> 2
B14: Churned clients | C14: 0 | D14: =ROUND(C15*$C$8,1) -> 0.1 | E14: =ROUND(D15*$C$8,1) -> 0.1 | F14: =ROUND(E15*$C$8,1) -> 0.2 | G14: =ROUND(F15*$C$8,1) -> 0.2 | H14: =ROUND(G15*$C$8,1) -> 0.3 | I14: =ROUND(H15*$C$8,1) -> 0.3 | J14: =ROUND(I15*$C$8,1) -> 0.4 | K14: =ROUND(J15*$C$8,1) -> 0.4 | ... N14: =ROUND(M15*$C$8,1) -> 0.6
B15: Active clients | C15: =C13 -> 2 | D15: =C15+D13-D14 -> 3.9 | E15: =D15+E13-E14 -> 5.8 | F15: =E15+F13-F14 -> 7.6 | G15: =F15+G13-G14 -> 9.4 | H15: =G15+H13-H14 -> 11.1 | I15: =H15+I13-I14 -> 12.8 | J15: =I15+J13-J14 -> 14.4 | K15: =J15+K13-K14 -> 16 | ... N15: =M15+N13-N14 -> 20.4
B16: Setup revenue (₹) | C16: =C13*$C$6 -> 89998 | D16: =D13*$C$6 -> 89998 | E16: =E13*$C$6 -> 89998 | F16: =F13*$C$6 -> 89998 | G16: =G13*$C$6 -> 89998 | H16: =H13*$C$6 -> 89998 | I16: =I13*$C$6 -> 89998 | J16: =J13*$C$6 -> 89998 | ... N16: =N13*$C$6 -> 89998
B17: Recurring revenue (₹) | C17: =C15*$C$7 -> 4998 | D17: =D15*$C$7 -> 9746.1 | E17: =E15*$C$7 -> 14494.2 | F17: =F15*$C$7 -> 18992.4 | G17: =G15*$C$7 -> 23490.6 | H17: =H15*$C$7 -> 27738.9 | I17: =I15*$C$7 -> 31987.2 | J17: =J15*$C$7 -> 35985.6 | ... N17: =N15*$C$7 -> 50979.6
B18: Total revenue (₹) | C18: =C16+C17 -> 94996 | D18: =D16+D17 -> 99744.1 | E18: =E16+E17 -> 104492.2 | F18: =F16+F17 -> 108990.4 | G18: =G16+G17 -> 113488.6 | H18: =H16+H17 -> 117736.9 | I18: =I16+I17 -> 121985.2 | J18: =J16+J17 -> 125983.6 | ... N18: =N16+N17 -> 140977.6
B19: Hosting cost (₹) | C19: =C15*$C$9 -> 400 | D19: =D15*$C$9 -> 780 | E19: =E15*$C$9 -> 1160 | F19: =F15*$C$9 -> 1520 | G19: =G15*$C$9 -> 1880 | H19: =H15*$C$9 -> 2220 | I19: =I15*$C$9 -> 2560 | J19: =J15*$C$9 -> 2880 | ... N19: =N15*$C$9 -> 4080
B20: Gross profit (₹) | C20: =C18-C19 -> 94596 | D20: =D18-D19 -> 98964.1 | E20: =E18-E19 -> 103332.2 | F20: =F18-F19 -> 107470.4 | G20: =G18-G19 -> 111608.6 | H20: =H18-H19 -> 115516.9 | I20: =I18-I19 -> 119425.2 | J20: =J18-J19 -> 123103.6 | ... N20: =N18-N19 -> 136897.6
B21: MRR (₹) | C21: =C17 -> 4998 | D21: =D17 -> 9746.1 | E21: =E17 -> 14494.2 | F21: =F17 -> 18992.4 | G21: =G17 -> 23490.6 | H21: =H17 -> 27738.9 | I21: =I17 -> 31987.2 | J21: =J17 -> 35985.6 | ... N21: =N17 -> 50979.6
B22: ARR run-rate (₹) | C22: =C21*12 -> 59976 | D22: =D21*12 -> 116953.2 | E22: =E21*12 -> 173930.4 | F22: =F21*12 -> 227908.8 | G22: =G21*12 -> 281887.2 | H22: =H21*12 -> 332866.8 | I22: =I21*12 -> 383846.4 | J22: =J21*12 -> 431827.2 | ... N22: =N21*12 -> 611755.2
B24: Year 1 totals
B25: Total revenue | C25: =SUM(C18:N18) -> 1429586.1
B26: Total gross profit | C26: =SUM(C20:N20) -> 1401606.1
B27: Exit MRR (month 12) | C27: =N21 -> 50979.6
B28: Exit ARR run-rate | C28: =N22 -> 611755.2
B30: Note: at roughly 8 active clients, deploy-per-clinic ops stop scaling. Gap report §1.4 covers the multi-tenant migration.

Sheet Dashboard
A1: Dashboard
A2: Read-only. All figures pull from the Pipeline sheet.
B4: PIPELINE BY STAGE
B5: Not Contacted | C5: =COUNTIF(Pipeline!$O$5:$O$204,"Not Contacted") -> 0
B6: Contacted | C6: =COUNTIF(Pipeline!$O$5:$O$204,"Contacted") -> 0
B7: Replied | C7: =COUNTIF(Pipeline!$O$5:$O$204,"Replied") -> 0
B8: Demo Booked | C8: =COUNTIF(Pipeline!$O$5:$O$204,"Demo Booked") -> 1
B9: Demo Done | C9: =COUNTIF(Pipeline!$O$5:$O$204,"Demo Done") -> 0
B10: Proposal Sent | C10: =COUNTIF(Pipeline!$O$5:$O$204,"Proposal Sent") -> 0
B11: Closed Won | C11: =COUNTIF(Pipeline!$O$5:$O$204,"Closed Won") -> 0
B12: Closed Lost | C12: =COUNTIF(Pipeline!$O$5:$O$204,"Closed Lost") -> 0
B13: Nurture | C13: =COUNTIF(Pipeline!$O$5:$O$204,"Nurture") -> 0
B14: Total prospects | C14: =COUNTA(Pipeline!$A$5:$A$204) -> 1
B16: CONVERSION
B17: Contacted → Replied | C17: =IFERROR((C7+C8+C9+C10+C11)/(C6+C7+C8+C9+C10+C11+C12),0) -> 1 | D17: Healthy: 8–15% on cold email
B18: Replied → Demo booked | C18: =IFERROR((C8+C9+C10+C11)/(C7+C8+C9+C10+C11+C12),0) -> 1 | D18: Healthy: ~40%
B19: Demo → Closed won | C19: =IFERROR(C11/(C9+C10+C11+C12),0) -> 0 | D19: Healthy: 25–35%. Below 20% = qualify harder, per Playbook §2
B20: Overall win rate | C20: =IFERROR(C11/C14,0) -> 0 | D20: Prospects contacted that became clients
B23: VALUE
B24: Closed-won setup revenue | C24: =SUMIF(Pipeline!$O$5:$O$204,"Closed Won",Pipeline!$L$5:$L$204) -> 0 | D24: Cash collected on setup fees
B25: Closed-won MRR | C25: =SUMIF(Pipeline!$O$5:$O$204,"Closed Won",Pipeline!$M$5:$M$204) -> 0 | D25: Recurring revenue you have won
B26: Closed-won ARR run-rate | C26: =C24*12 -> 0 | D26: MRR × 12
B27: Closed-won year-1 value | C27: =SUMIF(Pipeline!$O$5:$O$204,"Closed Won",Pipeline!$N$5:$N$204) -> 0 | D27: Setup + 12 months
B28: Open pipeline value | C28: =SUMIFS(Pipeline!$N$5:$N$204,Pipeline!$O$5:$O$204,"<>Closed Won",Pipeline!$O$5:$O$204,"<>Closed Lost") -> 74987 | D28: Year-1 value of everything not yet decided
B29: Avg deal size (won) | C29: =IFERROR(C26/C11,0) -> 0 | D29: Target: ₹75,000
B32: ACTIVITY
B33: Prospects with a next action | C33: =COUNTA(Pipeline!$P$5:$P$204) -> 1 | D33: Every live deal should have one
B34: Deals with no next action | C34: =MAX(0,C14-C6-C11-C12-C33) -> 0 | D34: These are the deals that quietly die
